doc/source/conf.py
etc/nginx/nginx.conf
etc/nginx/certs/localhost.crt
etc/nginx/certs/localhost.key
etc/statsd/config.js
nginx_statsd/__init__.py
nginx_statsd/app.py
nginx_statsd/logging.py
nginx_statsd/main.py
nginx_statsd/py.typed
nginx_statsd/settings.py
nginx_statsd/cli/__init__.py
nginx_statsd/cli/cli.py
nginx_statsd/cli/server.py
nginx_statsd_sidecar-0.2.1.dist-info/licenses/AUTHORS.txt
nginx_statsd_sidecar-0.2.1.dist-info/licenses/LICENSE.txt
nginx_statsd_sidecar-0.2.1.dist-info/METADATA
nginx_statsd_sidecar-0.2.1.dist-info/WHEEL
nginx_statsd_sidecar-0.2.1.dist-info/entry_points.txt
nginx_statsd_sidecar-0.2.1.dist-info/top_level.txt
nginx_statsd_sidecar-0.2.1.dist-info/RECORD
