Metadata-Version: 2.4
Name: nginx_statsd_sidecar
Version: 0.2.1
Summary: A sidecar for nginx to send statsd metrics to a statsd server
Author-email: Caltech IMSS ADS <imss-ads-staff@caltech.edu>
Maintainer-email: Christopher Malek <cmalek@caltech.edu>
License: Copyright 2025 California Institute of Technology.  Questions or comments
Project-URL: Homepage, https://github.com/caltechads/nginx_statsd_sidecar
Project-URL: Bug Reports, https://github.com/caltechads/nginx_statsd_sidecar/issues
Keywords: nginx,docker,monitoring,observability,statsd
Classifier: Development Status :: 5 - Production/Stable
Classifier: Intended Audience :: Developers
Classifier: Operating System :: OS Independent
Classifier: Programming Language :: Python
Classifier: Programming Language :: Python :: 3.11
Classifier: Programming Language :: Python :: 3.12
Classifier: Programming Language :: Python :: 3.13
Classifier: Framework :: AsyncIO
Classifier: Topic :: System :: Monitoring
Requires-Python: >=3.11
License-File: LICENSE.txt
License-File: AUTHORS.txt
Requires-Dist: aiodogstatsd>=0.16.0.post0
Requires-Dist: click>=8.0
Requires-Dist: psutil>=6.1.0
Requires-Dist: pydantic-settings>=2.10
Requires-Dist: httpx[http2]>=0.24.0
Requires-Dist: uvloop>=0.21.0
Requires-Dist: python-json-logger>=3.3.0
Requires-Dist: build>=1.3.0
Dynamic: license-file
